mvtToPng/__init__.py
mvtToPng/converter.py
mvttopng-1.0.10.dist-info/licenses/LICENSE
mvttopng-1.0.10.dist-info/METADATA
mvttopng-1.0.10.dist-info/WHEEL
mvttopng-1.0.10.dist-info/top_level.txt
mvttopng-1.0.10.dist-info/RECORD
