Metadata-Version: 2.4
Name: mvtToPng
Version: 1.0.10
Summary: Convert a vector tile to a png.
Author-email: Michael Keller <michaelkeller03@gmail.com>
License: MIT
Classifier: Programming Language :: Python :: 3
License-File: LICENSE
Requires-Dist: Fiona==1.10.1
Requires-Dist: geopandas==1.1.2
Requires-Dist: mapbox-vector-tile==2.1.0
Requires-Dist: matplotlib==3.10.8
Requires-Dist: pandas==2.3.3
Requires-Dist: Pillow==12.1.0
Requires-Dist: Shapely==2.1.2
Requires-Dist: vt2geojson==0.2.1
Requires-Dist: protobuf==5.29.5
Dynamic: license-file
